auto_syspath3/__init__.py
auto_syspath3/setup.cfg
auto_syspath3-1.0.1.dist-info/METADATA
auto_syspath3-1.0.1.dist-info/WHEEL
auto_syspath3-1.0.1.dist-info/top_level.txt
auto_syspath3-1.0.1.dist-info/RECORD
