Metadata-Version: 2.1
Name: auto_syspath3
Version: 1.0.1
Home-page: https://github.com/Alan3344/auto_syspath3
Author: Alan3344
Author-email: cleverfairy23@gmail.com
Requires-Python: >=3.6, <4
